xlrd_compdoc_commented/__init__.py
xlrd_compdoc_commented/biffh.py
xlrd_compdoc_commented/book.py
xlrd_compdoc_commented/compdoc.py
xlrd_compdoc_commented/formatting.py
xlrd_compdoc_commented/formula.py
xlrd_compdoc_commented/info.py
xlrd_compdoc_commented/sheet.py
xlrd_compdoc_commented/timemachine.py
xlrd_compdoc_commented/xldate.py
xlrd_compdoc_commented/xlsx.py
xlrd_compdoc_commented-1.2.0.data/scripts/runxlrd.py
xlrd_deeson_test/__init__.py
xlrd_deeson_test/biffh.py
xlrd_deeson_test/book.py
xlrd_deeson_test/compdoc.py
xlrd_deeson_test/formatting.py
xlrd_deeson_test/formula.py
xlrd_deeson_test/info.py
xlrd_deeson_test/sheet.py
xlrd_deeson_test/timemachine.py
xlrd_deeson_test/xldate.py
xlrd_deeson_test/xlsx.py
xlrd_compdoc_commented-1.2.0.dist-info/LICENSE
xlrd_compdoc_commented-1.2.0.dist-info/METADATA
xlrd_compdoc_commented-1.2.0.dist-info/WHEEL
xlrd_compdoc_commented-1.2.0.dist-info/top_level.txt
xlrd_compdoc_commented-1.2.0.dist-info/RECORD
